LICENSE
README.md
araviscam/BlackflyCam.py
araviscam/__init__.py
araviscam/camera.py
docs/Makefile
docs/araviscam.rst
docs/conf.py
docs/index.rst
docs/modules.rst
etc/BFS_PGE_16S7.xml
etc/cameras.yaml
sdss_araviscam-0.2.4.dist-info/LICENSE
sdss_araviscam-0.2.4.dist-info/METADATA
sdss_araviscam-0.2.4.dist-info/WHEEL
sdss_araviscam-0.2.4.dist-info/entry_points.txt
sdss_araviscam-0.2.4.dist-info/RECORD
