Metadata-Version: 2.1
Name: sdss-araviscam
Version: 0.2.4
Summary: Blackfly S GigE camera reader for SDSS-V/LVM
Home-page: https://wiki.sdss.org
License: BSD-3-Clause
Keywords: SDSS-V,LVM
Author: Richard J. Mathar
Author-email: mathar@mpia-hd.mpg.de
Requires-Python: >=3.7,<4
Classifier: Development Status :: 3 - Alpha
Classifier: License :: OSI Approved :: BSD License
Classifier: Natural Language :: English
Classifier: Operating System :: OS Independent
Classifier: Programming Language :: Python :: 3
Classifier: Programming Language :: Python :: 3.7
Classifier: Programming Language :: Python :: 3.8
Classifier: Programming Language :: Python :: 3.9
Classifier: Programming Language :: Python :: 3.10
Classifier: Programming Language :: Python :: 3.11
Classifier: Topic :: Multimedia :: Video :: Capture
Classifier: Topic :: Scientific/Engineering :: Astronomy
Requires-Dist: PyGObject (>=3.38.0)
Requires-Dist: sdss-basecam (>=0.5.0)
Project-URL: Repository, https://github.com/sdss/araviscam
